pyproject.toml
setup.py
hebi/__init__.py
hebi/arm.py
hebi/config.py
hebi/robot_model.py
hebi/trajectory.py
hebi/util.py
hebi/version.py
hebi/_internal/__init__.py
hebi/_internal/debug.py
hebi/_internal/errors.py
hebi/_internal/field_bindings.py
hebi/_internal/graphics.py
hebi/_internal/group.py
hebi/_internal/kinematics.py
hebi/_internal/log_file.py
hebi/_internal/lookup.py
hebi/_internal/math_utils.py
hebi/_internal/mobile_io.py
hebi/_internal/trajectory.py
hebi/_internal/type_utils.py
hebi/_internal/utils.py
hebi/_internal/ffi/__init__.py
hebi/_internal/ffi/_marshalling.py
hebi/_internal/ffi/_message_enums.py
hebi/_internal/ffi/_message_types.py
hebi/_internal/ffi/ctypes_caches.py
hebi/_internal/ffi/ctypes_defs.py
hebi/_internal/ffi/ctypes_loader.py
hebi/_internal/ffi/ctypes_utils.py
hebi/_internal/ffi/enums.py
hebi/_internal/ffi/loader.py
hebi/_internal/ffi/profiler.py
hebi/_internal/ffi/wrappers.py
hebi/lib/linux_aarch64/libhebi.so
hebi/lib/linux_aarch64/libhebi.so.2
hebi/lib/linux_aarch64/libhebi.so.2.22
hebi/lib/linux_aarch64/libhebi.so.2.22.1
hebi/lib/linux_x86_64/libhebi.so
hebi/lib/linux_x86_64/libhebi.so.2
hebi/lib/linux_x86_64/libhebi.so.2.22
hebi/lib/linux_x86_64/libhebi.so.2.22.1
hebi/lib/osx/libhebi.2.22.1.dylib
hebi/lib/osx/libhebi.2.22.dylib
hebi/lib/osx/libhebi.2.dylib
hebi/lib/osx/libhebi.dylib
hebi/lib/win_x64/hebi.dll
hebi_py.egg-info/PKG-INFO
hebi_py.egg-info/SOURCES.txt
hebi_py.egg-info/dependency_links.txt
hebi_py.egg-info/requires.txt
hebi_py.egg-info/top_level.txt