Metadata-Version: 2.4
Name: hebi-py
Version: 2.12.0
Summary: HEBI Core Python bindings
Home-page: https://docs.hebi.us
Author-email: Chris Bollinger <chris@hebirobotics.com>, Chris Bollinger <support@hebirobotics.com>
Project-URL: API Reference, https://files.hebi.us/docs/python/2.12.0/
Project-URL: Changelog, http://docs.hebi.us/downloads_changelogs.html#python-api-changelog
Project-URL: Documentation, http://docs.hebi.us/tools.html#python-api
Project-URL: Examples, https://github.com/HebiRobotics/hebi-python-examples
Classifier: Development Status :: 5 - Production/Stable
Classifier: Environment :: MacOS X
Classifier: Intended Audience :: Developers
Classifier: Operating System :: MacOS
Classifier: Operating System :: Microsoft :: Windows
Classifier: Operating System :: POSIX
Classifier: Operating System :: Unix
Classifier: Programming Language :: Python :: 3
Classifier: Programming Language :: Python :: Implementation :: CPython
Requires-Python: >=3.9
Requires-Dist: setuptools>=80.9.0
Requires-Dist: numpy>=1.26
Requires-Dist: pyyaml>=3.13
Dynamic: description
Dynamic: description-content-type
Dynamic: home-page
Dynamic: project-url
